{
  "_meta": {
    "source": "KitchenDOOR",
    "site": "rexdale",
    "exported": "2026-04-30T17:25:40.281Z",
    "version": 29
  },
  "menu": {
    "1": {
      "SUNDAY": {
        "breakfast": "Pork Breakfast sandwich",
        "breakfast_veg": "Vegan Breakfast Sausage Sandwich",
        "breakfast_softAlt": "Plain English Muffin, Scrambled Eggs x2, DF Yoghurt & Fruit",
        "allergens_breakfast": "gluten, egg, dairy, pork",
        "lunch": "Turkey & Cheese, Seasonal Soup, Seasonal Soup",
        "lunch_veg": "Vegetarian Sandwich, Seasonal Soup, Seasonal Soup",
        "lunch_softAlt": "Plain Turkey, Soft Bread & Seasonal Soup",
        "allergens_lunch": "gluten, Turkey , dairy",
        "dinner": "Beef Strogonoff, Noodles",
        "dinner_veg": "Mushroom strogonoff, Noodles",
        "dinner_softAlt": "Plain Chicken Leg, Plain Rice & Stir-fried Veg",
        "allergens_dinner": "gluten, beef",
        "breakfast_flags": {
          "hasGluten": true,
          "hasDairy": true,
          "hasPork": true,
          "hasFish": false,
          "hasEgg": true,
          "hasPeanuts": false,
          "hasSesame": false,
          "hasSoy": false,
          "hasBeef": false,
          "isSpicy": false,
          "isCarb": true,
          "hasProcessedMeat": true
        },
        "lunch_flags": {
          "hasGluten": true,
          "hasDairy": true,
          "hasEgg": false,
          "hasFish": false,
          "hasPeanuts": false,
          "hasSoy": false,
          "hasTreeNuts": false,
          "hasSesame": false,
          "hasMustard": false,
          "hasShellfish": false,
          "hasSulphites": false,
          "hasPork": false,
          "hasBeef": false,
          "hasChicken": false,
          "hasTurkey": true,
          "isSpicy": false,
          "isCarb": false,
          "halalCertifiedMeat": true,
          "hasProcessedMeat": false,
          "hasBeans": false,
          "hasMushroom": false,
          "hasCoconut": false,
          "hasNightshades": false,
          "hasBrassicas": false,
          "hasCorn": false
        },
        "dinner_flags": {
          "hasGluten": true,
          "hasDairy": false,
          "hasPork": false,
          "hasFish": false,
          "hasEgg": false,
          "hasPeanuts": false,
          "hasSesame": false,
          "hasSoy": false,
          "hasBeef": true,
          "halalCertifiedMeat": true,
          "isSpicy": false,
          "isCarb": false
        }
      },
      "MONDAY": {
        "breakfast": "Pancakes, turkey bacon",
        "breakfast_veg": "Pancakes, Vegan Breakfast Sausage",
        "breakfast_softAlt": "Plain English Muffin, Scrambled Eggs x2, DF Yoghurt & Fruit",
        "allergens_breakfast": "gluten, dairy, egg, turkey",
        "lunch": "Halal Sausages & Baked Beans, Peas and Potatoes, Peas and Potatoes",
        "lunch_veg": "Vegan Sausages, Baked beans, Peas and Potatoes, Peas and Potatoes",
        "lunch_softAlt": "Mashed Potato, Baked Beans & Peas",
        "allergens_lunch": "gluten, beef",
        "dinner": "Jerk Chicken, Rice and Beans, Cabbage Stirfry",
        "dinner_veg": "Jerk Cauliflower, Rice and Beans, Cabbage Stirfry",
        "dinner_softAlt": "Roasted Chicken Leg, Cabbage & Carrot Stir-fry, Plain Rice & Peas",
        "allergens_dinner": "",
        "breakfast_flags": {
          "hasGluten": true,
          "hasDairy": true,
          "hasPork": false,
          "hasFish": false,
          "hasEgg": true,
          "hasPeanuts": false,
          "hasSesame": false,
          "hasSoy": false,
          "hasBeef": false,
          "isSpicy": false,
          "isCarb": false,
          "hasProcessedMeat": true
        },
        "lunch_flags": {
          "hasGluten": true,
          "hasDairy": false,
          "hasEgg": false,
          "hasFish": false,
          "hasPeanuts": false,
          "hasSoy": false,
          "hasTreeNuts": false,
          "hasSesame": false,
          "hasMustard": false,
          "hasShellfish": false,
          "hasSulphites": false,
          "hasPork": false,
          "hasBeef": false,
          "hasChicken": false,
          "hasTurkey": false,
          "isSpicy": false,
          "isCarb": true,
          "halalCertifiedMeat": true,
          "hasProcessedMeat": true,
          "hasBeans": false,
          "hasMushroom": false,
          "hasCoconut": false,
          "hasNightshades": false,
          "hasBrassicas": false,
          "hasCorn": false
        },
        "dinner_flags": {
          "hasGluten": false,
          "hasDairy": false,
          "hasEgg": false,
          "hasFish": false,
          "hasPeanuts": false,
          "hasSoy": false,
          "hasTreeNuts": false,
          "hasSesame": false,
          "hasMustard": false,
          "hasShellfish": false,
          "hasSulphites": false,
          "hasPork": false,
          "hasBeef": false,
          "hasChicken": true,
          "hasTurkey": false,
          "isSpicy": true,
          "isCarb": true,
          "halalCertifiedMeat": true,
          "hasProcessedMeat": false,
          "hasBeans": false,
          "hasMushroom": false,
          "hasCoconut": false,
          "hasNightshades": false,
          "hasBrassicas": false,
          "hasCorn": false
        }
      },
      "TUESDAY": {
        "breakfast": "Cereal and milk",
        "breakfast_veg": "Cereal and milk",
        "allergens_breakfast": "dairy, gluten",
        "lunch": "Blackened fish, Sweet potatoes, Seasonal Vegetables",
        "lunch_veg": "Roasted Tofu, Sweet potatoes, Seasonal Vegetables",
        "lunch_softAlt": "Baked Plain Fish, Mashed Sweet Potato & Seasonal Veg",
        "allergens_lunch": "fish, soy",
        "dinner": "Pork Carnitas, Spanish rice and vegetables",
        "dinner_veg": "Vegetarian carnitas, Spanish rice and vegetables",
        "dinner_softAlt": "Plain Chicken Leg, Plain Rice & Stir-fried Veg",
        "dinner_halal": "Halal Chicken carnitas",
        "allergens_dinner": "pork",
        "breakfast_flags": {
          "hasGluten": true,
          "hasDairy": true,
          "hasPork": false,
          "hasFish": false,
          "hasEgg": false,
          "hasPeanuts": false,
          "hasSesame": false,
          "hasSoy": false,
          "hasBeef": false,
          "isSpicy": false,
          "isCarb": false
        },
        "lunch_flags": {
          "hasGluten": false,
          "hasDairy": false,
          "hasPork": false,
          "hasFish": true,
          "hasEgg": false,
          "hasPeanuts": false,
          "hasSesame": false,
          "hasSoy": true,
          "hasBeef": false,
          "isSpicy": false,
          "isCarb": false
        },
        "dinner_flags": {
          "hasGluten": false,
          "hasDairy": false,
          "hasPork": true,
          "hasFish": false,
          "hasEgg": false,
          "hasPeanuts": false,
          "hasSesame": false,
          "hasSoy": false,
          "hasBeef": false,
          "isSpicy": false,
          "isCarb": false
        }
      },
      "WEDNESDAY": {
        "breakfast": "Vegetarian Frittata",
        "breakfast_veg": "Vegetarian Frittata",
        "breakfast_softAlt": "Plain English Muffin, Scrambled Eggs x2, DF Yoghurt & Fruit",
        "allergens_breakfast": "gluten, dairy",
        "lunch": "Ham Mac & Cheese, Pea and Carrot",
        "lunch_veg": "Vegan Cauliflower Mac & Cheese, Pea and Carrot",
        "lunch_softAlt": "Plain Mac & Cheese (no ham), Peas & Carrots",
        "allergens_lunch": "pork, gluten, dairy",
        "dinner": "Roast Chicken & Chickpea Shakshuka, Couscous",
        "dinner_veg": "Roast Tofu, Chickpea Shakshuka, Couscous",
        "dinner_softAlt": "Plain Roasted Chicken, Stir-fried Veg & Rice",
        "allergens_dinner": "Gluten,",
        "breakfast_flags": {
          "hasGluten": true,
          "hasDairy": true,
          "hasPork": false,
          "hasFish": false,
          "hasEgg": false,
          "hasPeanuts": false,
          "hasSesame": false,
          "hasSoy": false,
          "hasBeef": false,
          "isSpicy": false,
          "isCarb": false
        },
        "lunch_flags": {
          "hasGluten": true,
          "hasDairy": true,
          "hasPork": true,
          "hasFish": false,
          "hasEgg": false,
          "hasPeanuts": false,
          "hasSesame": false,
          "hasSoy": false,
          "hasBeef": false,
          "isSpicy": false,
          "isCarb": true,
          "hasProcessedMeat": true
        },
        "dinner_flags": {
          "hasGluten": true,
          "hasDairy": false,
          "hasEgg": false,
          "hasFish": false,
          "hasPeanuts": false,
          "hasSoy": false,
          "hasTreeNuts": false,
          "hasSesame": false,
          "hasMustard": false,
          "hasShellfish": false,
          "hasSulphites": false,
          "hasPork": false,
          "hasBeef": false,
          "hasChicken": true,
          "hasTurkey": false,
          "isSpicy": false,
          "isCarb": true,
          "halalCertifiedMeat": true,
          "hasProcessedMeat": false,
          "hasBeans": false,
          "hasMushroom": false,
          "hasCoconut": false,
          "hasNightshades": false,
          "hasBrassicas": false,
          "hasCorn": false
        }
      },
      "THURSDAY": {
        "breakfast": "Scrambled eggs & sausage",
        "breakfast_veg": "Scrambled eggs & veg sausage",
        "breakfast_softAlt": "Soft Scrambled Eggs, DF Yoghurt & Fruit",
        "allergens_breakfast": "gluten, dairy, egg, pork",
        "lunch": "Chicken burger & Home Fries",
        "lunch_veg": "Crispy Quinoa Cake, Home Fries",
        "lunch_softAlt": "Plain Chicken Leg, Mashed Potato & Seasonal Veg",
        "allergens_lunch": "gluten, dairy",
        "dinner": "Butter Chicken & Vegetables, Naan",
        "dinner_veg": "Butter Chickpeas, Vegetables, Naan",
        "dinner_softAlt": "Baked Basa, Plain Rice & Stir-fried Veg",
        "allergens_dinner": "Halal Chicken",
        "breakfast_flags": {
          "hasGluten": true,
          "hasDairy": true,
          "hasPork": true,
          "hasFish": false,
          "hasEgg": true,
          "hasPeanuts": false,
          "hasSesame": false,
          "hasSoy": false,
          "hasBeef": false,
          "isSpicy": false,
          "isCarb": false,
          "hasProcessedMeat": true
        },
        "lunch_flags": {
          "hasGluten": true,
          "hasDairy": true,
          "hasEgg": false,
          "hasFish": false,
          "hasPeanuts": false,
          "hasSoy": false,
          "hasTreeNuts": false,
          "hasSesame": false,
          "hasMustard": false,
          "hasShellfish": false,
          "hasSulphites": false,
          "hasPork": false,
          "hasBeef": false,
          "hasChicken": true,
          "hasTurkey": false,
          "isSpicy": false,
          "isCarb": true,
          "halalCertifiedMeat": true,
          "hasProcessedMeat": false,
          "hasBeans": false,
          "hasMushroom": false,
          "hasCoconut": false,
          "hasNightshades": false,
          "hasBrassicas": false,
          "hasCorn": false
        },
        "dinner_flags": {
          "hasGluten": false,
          "hasDairy": false,
          "hasEgg": false,
          "hasFish": false,
          "hasPeanuts": false,
          "hasSoy": false,
          "hasTreeNuts": false,
          "hasSesame": false,
          "hasMustard": false,
          "hasShellfish": false,
          "hasSulphites": false,
          "hasPork": false,
          "hasBeef": false,
          "hasChicken": true,
          "hasTurkey": false,
          "isSpicy": false,
          "isCarb": true,
          "halalCertifiedMeat": true,
          "hasProcessedMeat": false,
          "hasBeans": false,
          "hasMushroom": false,
          "hasCoconut": false,
          "hasNightshades": false,
          "hasBrassicas": false,
          "hasCorn": false
        }
      },
      "FRIDAY": {
        "breakfast": "Turkey & Cheese and Eggs yoghurt",
        "breakfast_veg": "Oatmeal",
        "breakfast_softAlt": "Soft Scrambled Eggs, DF Yoghurt & Fruit",
        "allergens_breakfast": "turkey, gluten, dairy ,egg",
        "lunch": "Honey BBQ Halal Chicken Drumsticks, Potato Salad",
        "lunch_veg": "Vegan Drumsticks, Potato Salad",
        "lunch_softAlt": "Plain Chicken Leg, Mashed Potato & Seasonal Veg",
        "allergens_lunch": "Halal Chicken, Gluten, Egg",
        "dinner": "Pork Adobo with Vegetarian and Pineapple Rice",
        "dinner_veg": "Vegetarian Adobo with Vegetarian and Pineapple Rice",
        "dinner_softAlt": "Plain Chicken Leg, Plain Rice & Stir-fried Veg",
        "dinner_halal": "Halal Chicken Adobo",
        "allergens_dinner": "Pork",
        "breakfast_flags": {
          "hasGluten": true,
          "hasDairy": true,
          "hasEgg": true,
          "hasFish": false,
          "hasPeanuts": false,
          "hasSoy": false,
          "hasTreeNuts": false,
          "hasSesame": false,
          "hasMustard": false,
          "hasShellfish": false,
          "hasSulphites": false,
          "hasPork": false,
          "hasBeef": false,
          "hasChicken": false,
          "hasTurkey": true,
          "isSpicy": false,
          "isCarb": false,
          "halalCertifiedMeat": true,
          "hasProcessedMeat": false,
          "hasBeans": false,
          "hasMushroom": false,
          "hasCoconut": false,
          "hasNightshades": false,
          "hasBrassicas": false,
          "hasCorn": false
        },
        "lunch_flags": {
          "hasGluten": true,
          "hasDairy": false,
          "hasPork": false,
          "hasFish": false,
          "hasEgg": true,
          "hasPeanuts": false,
          "hasSesame": false,
          "hasSoy": false,
          "hasBeef": false,
          "hasChicken": true,
          "isSpicy": false,
          "isCarb": false,
          "halalCertifiedMeat": true
        },
        "dinner_flags": {
          "hasGluten": false,
          "hasDairy": false,
          "hasPork": true,
          "hasFish": false,
          "hasEgg": false,
          "hasPeanuts": false,
          "hasSesame": false,
          "hasSoy": false,
          "hasBeef": false,
          "isSpicy": false,
          "isCarb": false
        }
      },
      "SATURDAY": {
        "breakfast": "Bagel, Cream cheese and Granola.",
        "breakfast_veg": "Bagel, Cream cheese and Granola.",
        "breakfast_softAlt": "Plain English Muffin, Scrambled Eggs x2, DF Yoghurt & Fruit",
        "allergens_breakfast": "gluten, dairy",
        "lunch": "Chicken Fajitas & Tortillas, Peas and Corn",
        "lunch_veg": "Vegetarian Fajitas, Tortillas, Peas and Corn",
        "lunch_softAlt": "Plain Chicken Leg, Plain Rice & Stir-fried Veg",
        "allergens_lunch": "Halal Chicken, Gluten",
        "dinner": "Gomen Besiga, Carrot Cabbage Fry, Rice",
        "dinner_veg": "Vegetarin Collard Stew, Carrot Cabbage Fry, Rice",
        "dinner_softAlt": "Roasted Chicken Leg, Vegetable Stir-fry & Plain Rice",
        "allergens_dinner": "Beef",
        "breakfast_flags": {
          "hasGluten": true,
          "hasDairy": true,
          "hasPork": false,
          "hasFish": false,
          "hasEgg": false,
          "hasPeanuts": false,
          "hasSesame": false,
          "hasSoy": false,
          "hasBeef": false,
          "isSpicy": false,
          "isCarb": false
        },
        "lunch_flags": {
          "hasGluten": true,
          "hasDairy": false,
          "hasEgg": false,
          "hasFish": false,
          "hasPeanuts": false,
          "hasSoy": false,
          "hasTreeNuts": false,
          "hasSesame": false,
          "hasMustard": false,
          "hasShellfish": false,
          "hasSulphites": false,
          "hasPork": false,
          "hasBeef": false,
          "hasChicken": true,
          "hasTurkey": false,
          "isSpicy": false,
          "isCarb": true,
          "halalCertifiedMeat": true,
          "hasProcessedMeat": false,
          "hasBeans": false,
          "hasMushroom": false,
          "hasCoconut": false,
          "hasNightshades": false,
          "hasBrassicas": false,
          "hasCorn": false
        },
        "dinner_flags": {
          "hasGluten": false,
          "hasDairy": false,
          "hasPork": false,
          "hasFish": false,
          "hasEgg": false,
          "hasPeanuts": false,
          "hasSesame": false,
          "hasSoy": false,
          "hasBeef": true,
          "halalCertifiedMeat": true,
          "isSpicy": false,
          "isCarb": false
        }
      }
    },
    "2": {
      "SUNDAY": {
        "breakfast": "Turkey Breakfast sandwich",
        "breakfast_veg": "Vegan Breakfast Sausage Sandwich",
        "breakfast_softAlt": "Plain English Muffin, Scrambled Eggs x2, DF Yoghurt & Fruit",
        "allergens_breakfast": "gluten, egg, dairy,",
        "lunch": "Philly Cheese Melt",
        "lunch_veg": "Portobello Cheese Melt",
        "lunch_softAlt": "Plain Chicken, Soft Bread & Seasonal Soup",
        "allergens_lunch": "gluten, dairy",
        "dinner": "Sausage and Vegetable Pasta",
        "dinner_veg": "Vegan Sausage and Vegetable Pasta",
        "dinner_softAlt": "Plain Chicken Leg, Plain Rice & Stir-fried Veg",
        "dinner_halal": "Halal Turkey Sausage",
        "allergens_dinner": "pork, gluten",
        "breakfast_flags": {
          "hasGluten": true,
          "hasDairy": true,
          "hasPork": false,
          "hasFish": false,
          "hasEgg": true,
          "hasPeanuts": false,
          "hasSesame": false,
          "hasSoy": false,
          "hasBeef": false,
          "isSpicy": false,
          "isCarb": true
        },
        "lunch_flags": {
          "hasGluten": true,
          "hasDairy": true,
          "hasEgg": false,
          "hasFish": false,
          "hasPeanuts": false,
          "hasSoy": false,
          "hasTreeNuts": false,
          "hasSesame": false,
          "hasMustard": false,
          "hasShellfish": false,
          "hasSulphites": false,
          "hasPork": false,
          "hasBeef": false,
          "hasChicken": false,
          "hasTurkey": false,
          "isSpicy": false,
          "isCarb": false,
          "halalCertifiedMeat": true,
          "hasProcessedMeat": false,
          "hasBeans": false,
          "hasMushroom": false,
          "hasCoconut": false,
          "hasNightshades": false,
          "hasBrassicas": false,
          "hasCorn": false
        },
        "dinner_flags": {
          "hasGluten": true,
          "hasDairy": false,
          "hasPork": true,
          "hasFish": false,
          "hasEgg": false,
          "hasPeanuts": false,
          "hasSesame": false,
          "hasSoy": false,
          "hasBeef": false,
          "isSpicy": false,
          "isCarb": true,
          "hasProcessedMeat": true
        }
      },
      "MONDAY": {
        "breakfast": "Pancakes, turkey bacon",
        "breakfast_veg": "Pancakes, Vegan Breakfast Sausage",
        "breakfast_softAlt": "Plain English Muffin, Scrambled Eggs x2, DF Yoghurt & Fruit",
        "allergens_breakfast": "gluten, dairy, egg,",
        "lunch": "Vegan Chilli ,  garlic bread",
        "lunch_veg": "Vegan Chilli ,  garlic bread",
        "lunch_softAlt": "Plain Chicken Leg, Stir-fried Veg & Plain Rice",
        "allergens_lunch": "gluten, dairy",
        "dinner": "West African Peanut Stew , Seasonal Vegetables, Rice",
        "dinner_veg": "Vegetarian  Peanut Stew , Seasonal Vegetables, Rice",
        "dinner_softAlt": "Plain Chicken Leg, Stir-fried Veg & Plain Rice (no peanuts)",
        "allergens_dinner": "PEANUTS",
        "breakfast_flags": {
          "hasGluten": true,
          "hasDairy": true,
          "hasPork": false,
          "hasFish": false,
          "hasEgg": true,
          "hasPeanuts": false,
          "hasSesame": false,
          "hasSoy": false,
          "hasBeef": false,
          "isSpicy": false,
          "isCarb": false,
          "hasProcessedMeat": true
        },
        "lunch_flags": {
          "hasGluten": true,
          "hasDairy": true,
          "hasPork": false,
          "hasFish": false,
          "hasEgg": false,
          "hasPeanuts": false,
          "hasSesame": false,
          "hasSoy": false,
          "hasBeef": false,
          "isSpicy": true,
          "isCarb": false
        },
        "dinner_flags": {
          "hasGluten": false,
          "hasDairy": false,
          "hasPork": false,
          "hasFish": false,
          "hasEgg": false,
          "hasPeanuts": true,
          "hasSesame": false,
          "hasSoy": false,
          "hasBeef": false,
          "isSpicy": false,
          "isCarb": false
        }
      },
      "TUESDAY": {
        "breakfast": "Cereal and milk",
        "breakfast_veg": "Cereal and milk",
        "allergens_breakfast": "dairy, gluten",
        "lunch": "Roast Chicken Leg, Chana Masala, Couscous",
        "lunch_veg": "Tofu Vegetable Curry, Chana Masala, Couscous",
        "lunch_softAlt": "Plain Roasted Chicken Leg, Veg & Rice (no tomato, potato or mushroom)",
        "allergens_lunch": "gluten",
        "dinner": "Pork Vindaloo, Seasonal Vegetables, Steamed Rice",
        "dinner_veg": "Vegetarian Vindaloo, Seasonal Vegetables, Steamed Rice",
        "dinner_softAlt": "Plain Roasted Chicken Leg, Steamed Rice & Veg (no broccoli or cauliflower)",
        "dinner_halal": "Chicken Vindaloo",
        "allergens_dinner": "pork",
        "breakfast_flags": {
          "hasGluten": true,
          "hasDairy": true,
          "hasPork": false,
          "hasFish": false,
          "hasEgg": false,
          "hasPeanuts": false,
          "hasSesame": false,
          "hasSoy": false,
          "hasBeef": false,
          "isSpicy": false,
          "isCarb": false
        },
        "lunch_flags": {
          "hasGluten": true,
          "hasDairy": false,
          "hasPork": false,
          "hasFish": false,
          "hasEgg": false,
          "hasPeanuts": false,
          "hasSesame": false,
          "hasSoy": false,
          "hasBeef": false,
          "hasChicken": true,
          "isSpicy": false,
          "isCarb": false
        },
        "dinner_flags": {
          "hasGluten": false,
          "hasDairy": false,
          "hasPork": true,
          "hasFish": false,
          "hasEgg": false,
          "hasPeanuts": false,
          "hasSesame": false,
          "hasSoy": false,
          "hasBeef": false,
          "isSpicy": true,
          "isCarb": false
        }
      },
      "WEDNESDAY": {
        "breakfast": "Vegetarian Frittata",
        "breakfast_veg": "Vegetarian Frittata",
        "breakfast_softAlt": "Plain English Muffin, Scrambled Eggs x2, DF Yoghurt & Fruit",
        "allergens_breakfast": "gluten, dairy",
        "lunch": "Fried Chicken and Sweet Potato Biscuit, Seasonal Vegetables",
        "lunch_veg": "Vegan Chik'n Tenders  & Sweet Potato Biscuit, Seasonal Vegetables",
        "lunch_softAlt": "Plain Chicken Leg, Mashed Sweet Potato & Seasonal Veg",
        "lunch_halal": "Halal breaded chicken burgers",
        "allergens_lunch": "gluten, dairy",
        "dinner": "Yetisse Fish, Okra and cassava stew,Coconut Rice and peas",
        "dinner_veg": "Spiced Tofu, Okra and cassava stew,Coconut Rice and peas",
        "dinner_softAlt": "Plain Basa, Plain Rice & Stir-fried Veg",
        "allergens_dinner": "Fish",
        "breakfast_flags": {
          "hasGluten": true,
          "hasDairy": true,
          "hasPork": false,
          "hasFish": false,
          "hasEgg": false,
          "hasPeanuts": false,
          "hasSesame": false,
          "hasSoy": false,
          "hasBeef": false,
          "isSpicy": false,
          "isCarb": false
        },
        "lunch_flags": {
          "hasGluten": false,
          "hasDairy": true,
          "hasPork": false,
          "hasFish": false,
          "hasEgg": false,
          "hasPeanuts": false,
          "hasSesame": false,
          "hasSoy": false,
          "hasBeef": false,
          "hasChicken": true,
          "isSpicy": false,
          "isCarb": true
        },
        "dinner_flags": {
          "hasGluten": false,
          "hasDairy": false,
          "hasPork": false,
          "hasFish": true,
          "hasEgg": false,
          "hasPeanuts": false,
          "hasSesame": false,
          "hasSoy": false,
          "hasBeef": false,
          "hasCoconut": true,
          "isSpicy": false,
          "isCarb": true
        }
      },
      "THURSDAY": {
        "breakfast": "Scrambled eggs & sausage",
        "breakfast_veg": "Scrambled eggs & veg sausage",
        "breakfast_softAlt": "Soft Scrambled Eggs, DF Yoghurt & Fruit",
        "allergens_breakfast": "gluten, dairy, egg, pork",
        "lunch": "CONC Salad - Beef, lettuce,  beans, red cabbage, carrots, cheese, pickled onion,  naan",
        "lunch_veg": "CONC Salad - Vegan Beef,lettuce, beans, red cabbage, carrots, cheese, pickled onion, naan",
        "lunch_softAlt": "Roasted Chicken Leg, Steamed Rice & Soft Veg Stir-fry",
        "allergens_lunch": "Gluten, dairy",
        "dinner": "Sausages & Mash, Gravy, Green peas",
        "dinner_veg": "Vegan Sausages & Mash, Gravy, Green Peas",
        "dinner_softAlt": "Plain Roasted Chicken Leg, Steamed Rice, Peas, Carrots & Onions",
        "dinner_halal": "Halal beef sausages",
        "allergens_dinner": "pork",
        "breakfast_flags": {
          "hasGluten": true,
          "hasDairy": true,
          "hasPork": true,
          "hasFish": false,
          "hasEgg": true,
          "hasPeanuts": false,
          "hasSesame": false,
          "hasSoy": false,
          "hasBeef": false,
          "isSpicy": false,
          "isCarb": false,
          "hasProcessedMeat": true
        },
        "lunch_flags": {
          "hasGluten": true,
          "hasDairy": true,
          "hasPork": false,
          "hasFish": false,
          "hasEgg": false,
          "hasPeanuts": false,
          "hasSesame": false,
          "hasSoy": false,
          "hasBeef": true,
          "halalCertifiedMeat": true,
          "isSpicy": false,
          "isCarb": false
        },
        "dinner_flags": {
          "hasGluten": false,
          "hasDairy": false,
          "hasPork": true,
          "hasFish": false,
          "hasEgg": false,
          "hasPeanuts": false,
          "hasSesame": false,
          "hasSoy": false,
          "hasBeef": false,
          "isSpicy": false,
          "isCarb": false,
          "hasProcessedMeat": true
        }
      },
      "FRIDAY": {
        "breakfast": "Ham, Cheese and Eggs yoghurt",
        "breakfast_veg": "Oatmeal",
        "breakfast_softAlt": "Soft Scrambled Eggs, DF Yoghurt & Fruit",
        "allergens_breakfast": "pork, gluten, dairy ,egg",
        "lunch": "Tuna Salad Sandwich & Seasonal  Soup",
        "lunch_veg": "ّّFalafel Sandwich & Seasonal Soup",
        "lunch_softAlt": "Plain Fish or Tuna, Soft Bread & Seasonal Soup",
        "allergens_lunch": "fish, gluten",
        "dinner": "Arroz con Pollo,  Refried beans",
        "dinner_veg": "Vegan Arroz con pollo, Refried beans",
        "dinner_softAlt": "Plain Chicken Leg, Plain Rice & Stir-fried Veg",
        "allergens_dinner": "",
        "breakfast_flags": {
          "hasGluten": true,
          "hasDairy": true,
          "hasPork": true,
          "hasFish": false,
          "hasEgg": true,
          "hasPeanuts": false,
          "hasSesame": false,
          "hasSoy": false,
          "hasBeef": false,
          "isSpicy": false,
          "isCarb": false,
          "hasProcessedMeat": true
        },
        "lunch_flags": {
          "hasGluten": true,
          "hasDairy": false,
          "hasPork": false,
          "hasFish": true,
          "hasEgg": false,
          "hasPeanuts": false,
          "hasSesame": false,
          "hasSoy": false,
          "hasBeef": false,
          "isSpicy": false,
          "isCarb": true
        },
        "dinner_flags": {
          "hasGluten": false,
          "hasDairy": false,
          "hasPork": false,
          "hasFish": false,
          "hasEgg": false,
          "hasPeanuts": false,
          "hasSesame": false,
          "hasSoy": false,
          "hasBeef": false,
          "isSpicy": false,
          "isCarb": false
        }
      },
      "SATURDAY": {
        "breakfast": "Bagel, Cream cheese and Granola.",
        "breakfast_veg": "Bagel, Cream cheese and Granola.",
        "breakfast_softAlt": "Plain English Muffin, Scrambled Eggs x2, DF Yoghurt & Fruit",
        "allergens_breakfast": "gluten, dairy",
        "lunch": "Chicken tenders, Roasted Yams, Seasonal Veg",
        "lunch_veg": "Vegan Nuggets, Roasted Yams , Seasonal Veg",
        "lunch_softAlt": "Plain Roasted Chicken Leg, Roasted Yam & Seasonal Veg",
        "lunch_halal": "Halal breaded chicken burgers",
        "allergens_lunch": "gluten, dairy",
        "dinner": "Beef Meatloaf, Steamed vegetables, Potatoes",
        "dinner_veg": "Vegan Meatloaf, Steamed vegetables, Potatoes",
        "dinner_softAlt": "Plain Chicken Leg, Rice & Squash",
        "allergens_dinner": "",
        "breakfast_flags": {
          "hasGluten": true,
          "hasDairy": true,
          "hasPork": false,
          "hasFish": false,
          "hasEgg": false,
          "hasPeanuts": false,
          "hasSesame": false,
          "hasSoy": false,
          "hasBeef": false,
          "isSpicy": false,
          "isCarb": false
        },
        "lunch_flags": {
          "hasGluten": true,
          "hasDairy": true,
          "hasPork": false,
          "hasFish": false,
          "hasEgg": false,
          "hasPeanuts": false,
          "hasSesame": false,
          "hasSoy": false,
          "hasBeef": false,
          "hasChicken": true,
          "isSpicy": false,
          "isCarb": false
        },
        "dinner_flags": {
          "hasGluten": false,
          "hasDairy": false,
          "hasPork": false,
          "hasFish": false,
          "hasEgg": false,
          "hasPeanuts": false,
          "hasSesame": false,
          "hasSoy": false,
          "hasBeef": true,
          "halalCertifiedMeat": true,
          "isSpicy": false,
          "isCarb": false
        }
      }
    },
    "3": {
      "SUNDAY": {
        "breakfast": "Pork Breakfast sandwich",
        "breakfast_veg": "Vegan Breakfast Sausage Sandwich",
        "breakfast_softAlt": "Plain English Muffin, Scrambled Eggs x2, DF Yoghurt & Fruit",
        "allergens_breakfast": "gluten, egg, dairy,",
        "lunch": "Coronation Chicken Salad Sandwich",
        "lunch_veg": "Roasted Vegetable Sandwich",
        "lunch_softAlt": "Plain Chicken, Soft Bread & Seasonal Soup",
        "allergens_lunch": "gluten, egg,",
        "dinner": "Halal Beef Meatballs Pasta",
        "dinner_veg": "Vegan Meatballs Pasta",
        "dinner_softAlt": "Plain Chicken Leg, Plain Rice & Stir-fried Veg",
        "allergens_dinner": "gluten",
        "breakfast_flags": {
          "hasGluten": true,
          "hasDairy": true,
          "hasPork": true,
          "hasFish": false,
          "hasEgg": true,
          "hasPeanuts": false,
          "hasSesame": false,
          "hasSoy": false,
          "hasBeef": false,
          "isSpicy": false,
          "isCarb": true,
          "hasProcessedMeat": true
        },
        "lunch_flags": {
          "hasGluten": true,
          "hasDairy": false,
          "hasPork": false,
          "hasFish": false,
          "hasEgg": true,
          "hasPeanuts": false,
          "hasSesame": false,
          "hasSoy": false,
          "hasBeef": false,
          "hasChicken": true,
          "isSpicy": false,
          "isCarb": true
        },
        "dinner_flags": {
          "hasGluten": true,
          "hasDairy": false,
          "hasPork": false,
          "hasFish": false,
          "hasEgg": false,
          "hasPeanuts": false,
          "hasSesame": false,
          "hasSoy": false,
          "hasBeef": true,
          "isSpicy": false,
          "isCarb": true,
          "halalCertifiedMeat": true
        }
      },
      "MONDAY": {
        "breakfast": "Pancakes, turkey bacon",
        "breakfast_veg": "Pancakes, Vegan Breakfast Sausage",
        "breakfast_softAlt": "Plain English Muffin, Scrambled Eggs x2, DF Yoghurt & Fruit",
        "allergens_breakfast": "gluten, dairy, egg,",
        "lunch": "Vegan Chilli Cheese dogs",
        "lunch_veg": "Vegan Chilli Cheese dogs",
        "lunch_softAlt": "Plain Chicken Leg, Stir-fried Veg & Plain Rice",
        "allergens_lunch": "gluten, dairy",
        "dinner": "Roast Chicken, Morrocan rice and Seasonal Vegetables",
        "dinner_veg": "Roasted Portobello Mushrooms, Moroccan Rice and Seasonal Vegetables",
        "dinner_softAlt": "Plain Roasted Chicken, Plain Rice & Stir-fried Veg",
        "allergens_dinner": "",
        "breakfast_flags": {
          "hasGluten": true,
          "hasDairy": true,
          "hasPork": false,
          "hasFish": false,
          "hasEgg": true,
          "hasPeanuts": false,
          "hasSesame": false,
          "hasSoy": false,
          "hasBeef": false,
          "isSpicy": false,
          "isCarb": false,
          "hasProcessedMeat": true
        },
        "lunch_flags": {
          "hasGluten": false,
          "hasDairy": false,
          "hasEgg": false,
          "hasFish": false,
          "hasPeanuts": false,
          "hasSoy": false,
          "hasTreeNuts": false,
          "hasSesame": false,
          "hasMustard": false,
          "hasShellfish": false,
          "hasSulphites": false,
          "hasPork": false,
          "hasBeef": false,
          "isSpicy": false,
          "isCarb": false,
          "hasProcessedMeat": true,
          "hasBeans": false,
          "hasMushroom": false,
          "hasCoconut": false,
          "hasNightshades": false,
          "hasBrassicas": false,
          "hasCorn": false
        },
        "dinner_flags": {
          "hasGluten": false,
          "hasDairy": false,
          "hasPork": false,
          "hasFish": false,
          "hasEgg": false,
          "hasPeanuts": false,
          "hasSesame": false,
          "hasSoy": false,
          "hasBeef": false,
          "hasChicken": true,
          "isSpicy": false,
          "isCarb": false
        }
      },
      "TUESDAY": {
        "breakfast": "Cereal and milk",
        "breakfast_veg": "Cereal and milk",
        "allergens_breakfast": "dairy, gluten",
        "lunch": "Glazed Ham, Roast Potatoes, Garlic peas & corn",
        "lunch_veg": "Roast Potato and Tofu Hash, Garlic peas & Corn",
        "lunch_softAlt": "Plain Chicken Leg, Mashed Potato & Garlic Peas",
        "allergens_lunch": "pork",
        "dinner": "Caribbean Chicken Curry, Naan",
        "dinner_veg": "Caribbean Chickpea Curry, Naan",
        "dinner_softAlt": "Plain Roasted Chicken Leg, Steamed Rice & Seasonal Veg",
        "allergens_dinner": "gluten",
        "breakfast_flags": {
          "hasGluten": true,
          "hasDairy": true,
          "hasPork": false,
          "hasFish": false,
          "hasEgg": false,
          "hasPeanuts": false,
          "hasSesame": false,
          "hasSoy": false,
          "hasBeef": false,
          "isSpicy": false,
          "isCarb": false
        },
        "lunch_flags": {
          "hasGluten": false,
          "hasDairy": false,
          "hasPork": true,
          "hasFish": false,
          "hasEgg": false,
          "hasPeanuts": false,
          "hasSesame": false,
          "hasSoy": false,
          "hasBeef": false,
          "isSpicy": false,
          "isCarb": false,
          "hasProcessedMeat": true
        },
        "dinner_flags": {
          "hasGluten": true,
          "hasDairy": false,
          "hasPork": false,
          "hasFish": false,
          "hasEgg": false,
          "hasPeanuts": false,
          "hasSesame": false,
          "hasSoy": false,
          "hasBeef": false,
          "hasChicken": true,
          "isSpicy": false,
          "isCarb": false
        }
      },
      "WEDNESDAY": {
        "breakfast": "Ham Frittata",
        "breakfast_veg": "Vegetarian Frittata",
        "breakfast_softAlt": "Plain English Muffin, Scrambled Eggs x2, DF Yoghurt & Fruit",
        "allergens_breakfast": "gluten, dairy",
        "lunch": "Crispy Chicken Tender Wrap",
        "lunch_veg": "",
        "lunch_softAlt": "Plain Chicken Leg, Plain Rice & Stir-fried Veg",
        "allergens_lunch": "dairy, gluten",
        "dinner": "Baked Tomato Fish, Couscous, Seasonal Vegetables",
        "dinner_veg": "Baked Tomato Tofu, Couscous , Seasonal Vegetables",
        "dinner_softAlt": "Plain Basa, Plain Rice & Seasonal Veg",
        "allergens_dinner": "fish, gluten",
        "breakfast_flags": {
          "hasGluten": true,
          "hasDairy": true,
          "hasPork": true,
          "hasFish": false,
          "hasEgg": false,
          "hasPeanuts": false,
          "hasSesame": false,
          "hasSoy": false,
          "hasBeef": false,
          "isSpicy": false,
          "isCarb": false,
          "hasProcessedMeat": true
        },
        "lunch_flags": {
          "hasGluten": true,
          "hasDairy": true,
          "hasEgg": false,
          "hasFish": false,
          "hasPeanuts": false,
          "hasSoy": false,
          "hasTreeNuts": false,
          "hasSesame": false,
          "hasMustard": false,
          "hasShellfish": false,
          "hasSulphites": false,
          "hasPork": false,
          "hasBeef": false,
          "isSpicy": false,
          "isCarb": true,
          "halalCertifiedMeat": false,
          "hasProcessedMeat": true,
          "hasBeans": false,
          "hasMushroom": false,
          "hasCoconut": false,
          "hasNightshades": false,
          "hasBrassicas": false,
          "hasCorn": false
        },
        "dinner_flags": {
          "hasGluten": true,
          "hasDairy": false,
          "hasPork": false,
          "hasFish": true,
          "hasEgg": false,
          "hasPeanuts": false,
          "hasSesame": false,
          "hasSoy": false,
          "hasBeef": false,
          "isSpicy": false,
          "isCarb": false
        }
      },
      "THURSDAY": {
        "breakfast": "Scrambled eggs & sausage",
        "breakfast_veg": "Scrambled eggs & veg sausage",
        "breakfast_softAlt": "Soft Scrambled Eggs, DF Yoghurt & Fruit",
        "allergens_breakfast": "gluten, dairy, egg, pork",
        "lunch": "Beef Nachos Supreme, Tortilla chips, Sour Cream",
        "lunch_veg": "Vegetarian Nachos Supreme, Tortilla chips, Sour Cream",
        "lunch_softAlt": "Baked Plain Fish, Plain Rice & Stir-fried Veg",
        "allergens_lunch": "gluten,  dairy",
        "dinner": "Pork Griot, Chakalaka, Rice",
        "dinner_veg": "Citrus Tofu, Chakalaka, Rice",
        "dinner_softAlt": "Plain Chicken Leg, Roasted Potatoes & Stir-fried Veg",
        "allergens_dinner": "pork",
        "breakfast_flags": {
          "hasGluten": true,
          "hasDairy": true,
          "hasPork": true,
          "hasFish": false,
          "hasEgg": true,
          "hasPeanuts": false,
          "hasSesame": false,
          "hasSoy": false,
          "hasBeef": false,
          "isSpicy": false,
          "isCarb": false,
          "hasProcessedMeat": true
        },
        "lunch_flags": {
          "hasGluten": true,
          "hasDairy": true,
          "hasPork": false,
          "hasFish": false,
          "hasEgg": false,
          "hasPeanuts": false,
          "hasSesame": false,
          "hasSoy": false,
          "hasBeef": true,
          "halalCertifiedMeat": true,
          "isSpicy": false,
          "isCarb": true
        },
        "dinner_flags": {
          "hasGluten": false,
          "hasDairy": false,
          "hasPork": true,
          "hasFish": false,
          "hasEgg": false,
          "hasPeanuts": false,
          "hasSesame": false,
          "hasSoy": false,
          "hasBeef": false,
          "isSpicy": false,
          "isCarb": false
        }
      },
      "FRIDAY": {
        "breakfast": "Ham, Cheese and Eggs yoghurt",
        "breakfast_veg": "Oatmeal",
        "breakfast_softAlt": "Soft Scrambled Eggs, DF Yoghurt & Fruit",
        "allergens_breakfast": "pork, gluten, dairy ,egg",
        "lunch": "Nigerian Fish, Coconut Rice, Seasonal Veg",
        "lunch_veg": "Nigerian Tofu, Broccoli, Coconut Rice, Seasonal Veg",
        "lunch_softAlt": "Roasted Chicken Leg, Plain Rice & Stir-fried Veg",
        "allergens_lunch": "gluten",
        "dinner": "Chicken and Mushroom Fried Rice",
        "dinner_veg": "Soy-Free Mushroom Fried Rice",
        "dinner_softAlt": "Plain Chicken Leg, Steamed Rice & Seasonal Veg (no mushroom)",
        "allergens_dinner": "",
        "breakfast_flags": {
          "hasGluten": true,
          "hasDairy": true,
          "hasPork": true,
          "hasFish": false,
          "hasEgg": true,
          "hasPeanuts": false,
          "hasSesame": false,
          "hasSoy": false,
          "hasBeef": false,
          "isSpicy": false,
          "isCarb": false,
          "hasProcessedMeat": true
        },
        "lunch_flags": {
          "hasGluten": false,
          "hasDairy": false,
          "hasEgg": false,
          "hasFish": false,
          "hasPeanuts": false,
          "hasSoy": false,
          "hasTreeNuts": true,
          "hasSesame": false,
          "hasMustard": false,
          "hasShellfish": false,
          "hasSulphites": false,
          "hasPork": false,
          "hasBeef": false,
          "isSpicy": true,
          "isCarb": true,
          "hasProcessedMeat": false,
          "hasBeans": false,
          "hasMushroom": false,
          "hasCoconut": false,
          "hasNightshades": false,
          "hasBrassicas": false,
          "hasCorn": false
        },
        "dinner_flags": {
          "hasGluten": false,
          "hasDairy": false,
          "hasEgg": false,
          "hasFish": false,
          "hasPeanuts": false,
          "hasSoy": true,
          "hasTreeNuts": false,
          "hasSesame": true,
          "hasMustard": false,
          "hasShellfish": false,
          "hasSulphites": false,
          "hasPork": false,
          "hasBeef": false,
          "hasChicken": true,
          "hasTurkey": false,
          "isSpicy": false,
          "isCarb": true,
          "halalCertifiedMeat": true,
          "hasProcessedMeat": false,
          "hasBeans": false,
          "hasMushroom": true,
          "hasCoconut": false,
          "hasNightshades": false,
          "hasBrassicas": false,
          "hasCorn": false
        }
      },
      "SATURDAY": {
        "breakfast": "Bagel, Cream cheese and Granola.",
        "breakfast_veg": "Bagel, Cream cheese and Granola.",
        "breakfast_softAlt": "Plain English Muffin, Scrambled Eggs x2, DF Yoghurt & Fruit",
        "allergens_breakfast": "gluten, dairy",
        "lunch": "Sesame Chicken Stirfry, Seasonal Vegetables, Steamed Rice",
        "lunch_veg": "Sesame Tofu and Vegetable Stirfry, Steamed Rice",
        "lunch_softAlt": "Plain Chicken Leg, Steamed Rice & Seasonal Veg",
        "allergens_lunch": "sesame, soy",
        "dinner": "Pepperoni Pizza, Wedges, Seasonal soup",
        "dinner_veg": "Vegetarian Pizza, Wedges, Seasonal Soup",
        "dinner_softAlt": "Plain Chicken Leg, Plain Rice & Stir-fried Veg",
        "allergens_dinner": "gluten, pork, dairy",
        "breakfast_flags": {
          "hasGluten": true,
          "hasDairy": true,
          "hasPork": false,
          "hasFish": false,
          "hasEgg": false,
          "hasPeanuts": false,
          "hasSesame": false,
          "hasSoy": false,
          "hasBeef": false,
          "isSpicy": false,
          "isCarb": false
        },
        "lunch_flags": {
          "hasGluten": false,
          "hasDairy": false,
          "hasPork": false,
          "hasFish": false,
          "hasEgg": false,
          "hasPeanuts": false,
          "hasSesame": true,
          "hasSoy": true,
          "hasBeef": false,
          "hasChicken": true,
          "isSpicy": false,
          "isCarb": false
        },
        "dinner_flags": {
          "hasGluten": true,
          "hasDairy": true,
          "hasPork": true,
          "hasFish": false,
          "hasEgg": false,
          "hasPeanuts": false,
          "hasSesame": false,
          "hasSoy": false,
          "hasBeef": false,
          "isSpicy": false,
          "isCarb": true,
          "hasProcessedMeat": true
        }
      }
    },
    "4": {
      "SUNDAY": {
        "breakfast": "Turkey Breakfast sandwich",
        "breakfast_veg": "Vegan Breakfast Sausage Sandwich",
        "breakfast_softAlt": "Plain English Muffin, Scrambled Eggs x2, DF Yoghurt & Fruit",
        "allergens_breakfast": "gluten, egg, dairy,",
        "lunch": "Pork Souvlaki, Naan, Seasonal Vegetables, Tzatziki",
        "lunch_veg": "Black bean patty, Naan, Seasonal Vegetables,Tzatziki",
        "lunch_softAlt": "Plain Chicken Leg, Plain Rice & Stir-fried Veg",
        "allergens_lunch": "pork, gluten, dairy",
        "dinner": "White Chilli Chicken Pasta Casserole",
        "dinner_veg": "White Chilli Pasta Casserole",
        "dinner_softAlt": "Plain Chicken Leg, Rice & Broccoli",
        "allergens_dinner": "gluten",
        "breakfast_flags": {
          "hasGluten": true,
          "hasDairy": true,
          "hasPork": false,
          "hasFish": false,
          "hasEgg": true,
          "hasPeanuts": false,
          "hasSesame": false,
          "hasSoy": false,
          "hasBeef": false,
          "isSpicy": false,
          "isCarb": true
        },
        "lunch_flags": {
          "hasGluten": true,
          "hasDairy": true,
          "hasPork": true,
          "hasFish": false,
          "hasEgg": false,
          "hasPeanuts": false,
          "hasSesame": false,
          "hasSoy": false,
          "hasBeef": false,
          "isSpicy": false,
          "isCarb": true
        },
        "dinner_flags": {
          "hasGluten": true,
          "hasDairy": false,
          "hasPork": false,
          "hasFish": false,
          "hasEgg": false,
          "hasPeanuts": false,
          "hasSesame": false,
          "hasSoy": false,
          "hasBeef": false,
          "hasChicken": true,
          "isSpicy": true,
          "isCarb": true
        }
      },
      "MONDAY": {
        "breakfast": "Pancakes, turkey bacon",
        "breakfast_veg": "Pancakes, Vegan Breakfast Sausage",
        "breakfast_softAlt": "Plain English Muffin, Scrambled Eggs x2, DF Yoghurt & Fruit",
        "allergens_breakfast": "gluten, dairy, egg,",
        "lunch": "Chicken Ranch Salad Sandwich and Seasonal Soup",
        "lunch_veg": "Falafel  Sandwich and Seasonal Soup",
        "lunch_softAlt": "Plain Chicken, Soft Bread & Seasonal Soup",
        "allergens_lunch": "gluten, dairy",
        "dinner": "Fish Curry, Steamed Rice, Seasonal Vegetables",
        "dinner_veg": "Tofu Curry, Steamed Rice, Seasonal Vegetables",
        "dinner_softAlt": "Plain Fish, Plain Rice & Stir-fried Veg",
        "allergens_dinner": "fish",
        "breakfast_flags": {
          "hasGluten": true,
          "hasDairy": true,
          "hasPork": false,
          "hasFish": false,
          "hasEgg": true,
          "hasPeanuts": false,
          "hasSesame": false,
          "hasSoy": false,
          "hasBeef": false,
          "isSpicy": false,
          "isCarb": false,
          "hasProcessedMeat": true
        },
        "lunch_flags": {
          "hasGluten": true,
          "hasDairy": true,
          "hasPork": false,
          "hasFish": false,
          "hasEgg": false,
          "hasPeanuts": false,
          "hasSesame": false,
          "hasSoy": false,
          "hasBeef": false,
          "hasChicken": true,
          "isSpicy": false,
          "isCarb": true
        },
        "dinner_flags": {
          "hasGluten": false,
          "hasDairy": false,
          "hasPork": false,
          "hasFish": true,
          "hasEgg": false,
          "hasPeanuts": false,
          "hasSesame": false,
          "hasSoy": false,
          "hasBeef": false,
          "isSpicy": false,
          "isCarb": false
        }
      },
      "TUESDAY": {
        "breakfast": "Cereal and milk",
        "breakfast_veg": "Cereal and milk",
        "allergens_breakfast": "dairy, gluten",
        "lunch": "Pork Tacos Al Pastor, Garlic Corn",
        "lunch_veg": "Vegetarian Tacos, Garlic Corn",
        "lunch_softAlt": "Plain Chicken Leg, Plain Rice & Garlic Corn",
        "allergens_lunch": "pork, gluten, dairy",
        "dinner": "BBQ Chicken Leg, Roasted Sweet Potatoes, Seasonal Veg",
        "dinner_veg": "BBQ Chik'n Tenders, Roasted Sweet Potatoes, Seasonal Veg",
        "dinner_softAlt": "Plain Chicken Leg, Roasted Sweet Potato & Seasonal Veg",
        "allergens_dinner": "",
        "breakfast_flags": {
          "hasGluten": true,
          "hasDairy": true,
          "hasPork": false,
          "hasFish": false,
          "hasEgg": false,
          "hasPeanuts": false,
          "hasSesame": false,
          "hasSoy": false,
          "hasBeef": false,
          "isSpicy": false,
          "isCarb": false
        },
        "lunch_flags": {
          "hasGluten": true,
          "hasDairy": true,
          "hasEgg": false,
          "hasFish": false,
          "hasPeanuts": false,
          "hasSoy": false,
          "hasTreeNuts": false,
          "hasSesame": false,
          "hasMustard": false,
          "hasShellfish": false,
          "hasSulphites": false,
          "hasPork": true,
          "hasBeef": false,
          "hasChicken": false,
          "hasTurkey": false,
          "isSpicy": true,
          "isCarb": true,
          "halalCertifiedMeat": false,
          "hasProcessedMeat": false,
          "hasBeans": false,
          "hasMushroom": false,
          "hasCoconut": false,
          "hasNightshades": false,
          "hasBrassicas": false,
          "hasCorn": false
        },
        "dinner_flags": {
          "hasGluten": false,
          "hasDairy": false,
          "hasPork": false,
          "hasFish": false,
          "hasEgg": false,
          "hasPeanuts": false,
          "hasSesame": false,
          "hasSoy": false,
          "hasBeef": false,
          "hasChicken": true,
          "isSpicy": false,
          "isCarb": false
        }
      },
      "WEDNESDAY": {
        "breakfast": "Vegetarian Frittata",
        "breakfast_veg": "Vegetarian Frittata",
        "breakfast_softAlt": "Plain English Muffin, Scrambled Eggs x2, DF Yoghurt & Fruit",
        "allergens_breakfast": "gluten, dairy",
        "lunch": "Tuna Rex Salad",
        "lunch_veg": "Chickpea Rex Salad",
        "lunch_softAlt": "Plain Fish, Plain Rice & Seasonal Veg",
        "allergens_lunch": "fish",
        "dinner": "Beef and Vegetable Stew, Potatoes",
        "dinner_veg": "Vegan Pot Pie and Vegetable Medley",
        "dinner_softAlt": "Plain Chicken Leg, Plain Rice & Stir-fried Veg",
        "allergens_dinner": "",
        "breakfast_flags": {
          "hasGluten": true,
          "hasDairy": true,
          "hasPork": false,
          "hasFish": false,
          "hasEgg": false,
          "hasPeanuts": false,
          "hasSesame": false,
          "hasSoy": false,
          "hasBeef": false,
          "isSpicy": false,
          "isCarb": false
        },
        "lunch_flags": {
          "hasGluten": false,
          "hasDairy": false,
          "hasPork": false,
          "hasFish": true,
          "hasEgg": false,
          "hasPeanuts": false,
          "hasSesame": false,
          "hasSoy": false,
          "hasBeef": false,
          "isSpicy": false,
          "isCarb": false
        },
        "dinner_flags": {
          "hasGluten": false,
          "hasDairy": false,
          "hasPork": false,
          "hasFish": false,
          "hasEgg": false,
          "hasPeanuts": false,
          "hasSesame": false,
          "hasSoy": false,
          "hasBeef": true,
          "halalCertifiedMeat": true,
          "isSpicy": false,
          "isCarb": false
        }
      },
      "THURSDAY": {
        "breakfast": "Scrambled eggs & sausage",
        "breakfast_veg": "Scrambled eggs & veg sausage",
        "breakfast_softAlt": "Soft Scrambled Eggs, DF Yoghurt & Fruit",
        "allergens_breakfast": "gluten, dairy, egg, pork",
        "lunch": "Chicken Schwarma, Coleslaw. Mujadarrah Rice, Garlic Sauce",
        "lunch_veg": "Vegetarian Schwarma, Coleslaw. Mujadarrah Rice, Garlic Sauce",
        "lunch_softAlt": "Plain Chicken Leg, Plain Rice & Soft Veg",
        "allergens_lunch": "gluten",
        "dinner": "Teriyaki Chicken,  Vegetable Egg Noodles",
        "dinner_veg": "Teriyaki Tofu, Vegetable Egg Noodles",
        "dinner_softAlt": "Plain Roasted Chicken, Steamed Rice & Vegetables",
        "allergens_dinner": "Egg,soy,gluten,sesame",
        "breakfast_flags": {
          "hasGluten": true,
          "hasDairy": true,
          "hasPork": true,
          "hasFish": false,
          "hasEgg": true,
          "hasPeanuts": false,
          "hasSesame": false,
          "hasSoy": false,
          "hasBeef": false,
          "isSpicy": false,
          "isCarb": false,
          "hasProcessedMeat": true
        },
        "lunch_flags": {
          "hasGluten": true,
          "hasDairy": false,
          "hasPork": false,
          "hasFish": false,
          "hasEgg": false,
          "hasPeanuts": false,
          "hasSesame": false,
          "hasSoy": false,
          "hasBeef": false,
          "hasChicken": true,
          "isSpicy": false,
          "isCarb": false
        },
        "dinner_flags": {
          "hasGluten": true,
          "hasDairy": false,
          "hasPork": false,
          "hasFish": false,
          "hasEgg": true,
          "hasPeanuts": false,
          "hasSesame": true,
          "hasSoy": true,
          "hasBeef": false,
          "hasChicken": true,
          "isSpicy": false,
          "isCarb": false
        }
      },
      "FRIDAY": {
        "breakfast": "Ham, Cheese and Eggs yoghurt",
        "breakfast_veg": "Oatmeal",
        "breakfast_softAlt": "Soft Scrambled Eggs, DF Yoghurt & Fruit",
        "allergens_breakfast": "pork, gluten, dairy ,egg",
        "lunch": "Beef lasagna,  Seasonal Vegetables",
        "lunch_veg": "Beef lasagna,  Seasonal Vegetables",
        "lunch_softAlt": "Plain Chicken Leg, Plain Rice & Stir-fried Veg",
        "allergens_lunch": "gluten, dairy",
        "dinner": "Tandoori Pork & Vegetable Briyani, Rice",
        "dinner_veg": "Tandoori Tofu, Vegetable Briyani, Rice",
        "dinner_softAlt": "Plain Chicken Leg, Plain Rice & Stir-fried Veg",
        "dinner_halal": "Tandoori Chicken",
        "allergens_dinner": "Pork",
        "breakfast_flags": {
          "hasGluten": true,
          "hasDairy": true,
          "hasPork": true,
          "hasFish": false,
          "hasEgg": true,
          "hasPeanuts": false,
          "hasSesame": false,
          "hasSoy": false,
          "hasBeef": false,
          "isSpicy": false,
          "isCarb": false,
          "hasProcessedMeat": true
        },
        "lunch_flags": {
          "hasGluten": true,
          "hasDairy": true,
          "hasPork": false,
          "hasFish": false,
          "hasEgg": false,
          "hasPeanuts": false,
          "hasSesame": false,
          "hasSoy": false,
          "hasBeef": true,
          "halalCertifiedMeat": true,
          "isSpicy": false,
          "isCarb": true
        },
        "dinner_flags": {
          "hasGluten": false,
          "hasDairy": false,
          "hasEgg": false,
          "hasFish": false,
          "hasPeanuts": false,
          "hasSoy": false,
          "hasTreeNuts": false,
          "hasSesame": false,
          "hasMustard": false,
          "hasShellfish": false,
          "hasSulphites": false,
          "hasPork": true,
          "hasBeef": false,
          "hasChicken": false,
          "hasTurkey": false,
          "isSpicy": true,
          "isCarb": true,
          "halalCertifiedMeat": false,
          "hasProcessedMeat": false,
          "hasBeans": false,
          "hasMushroom": false,
          "hasCoconut": false,
          "hasNightshades": false,
          "hasBrassicas": false,
          "hasCorn": false
        }
      },
      "SATURDAY": {
        "breakfast": "Bagel, Cream cheese and Granola.",
        "breakfast_veg": "Bagel, Cream cheese and Granola.",
        "breakfast_softAlt": "Plain English Muffin, Scrambled Eggs x2, DF Yoghurt & Fruit",
        "allergens_breakfast": "gluten, dairy",
        "lunch": "Lime-Spiced Chicken Legs, Garlic Bread, Seasonal Veg",
        "lunch_veg": "Roasted Veg and Tofu Medley, Tumeric Quinoa, Garlic Bread",
        "lunch_softAlt": "Plain Chicken Leg, Steamed Rice & Seasonal Veg",
        "allergens_lunch": "gluten, dairy",
        "dinner": "Beef Massaman Curry, Rice",
        "dinner_veg": "Vegetarian Massaman Curry, Rice",
        "dinner_softAlt": "Plain Chicken Leg, Plain Rice & Stir-fried Veg",
        "allergens_dinner": "",
        "breakfast_flags": {
          "hasGluten": true,
          "hasDairy": true,
          "hasPork": false,
          "hasFish": false,
          "hasEgg": false,
          "hasPeanuts": false,
          "hasSesame": false,
          "hasSoy": false,
          "hasBeef": false,
          "isSpicy": false,
          "isCarb": false
        },
        "lunch_flags": {
          "hasGluten": true,
          "hasDairy": true,
          "hasPork": false,
          "hasFish": false,
          "hasEgg": false,
          "hasPeanuts": false,
          "hasSesame": false,
          "hasSoy": false,
          "hasBeef": false,
          "hasChicken": true,
          "isSpicy": false,
          "isCarb": false
        },
        "dinner_flags": {
          "hasGluten": false,
          "hasDairy": false,
          "hasPork": false,
          "hasFish": false,
          "hasEgg": false,
          "hasPeanuts": true,
          "hasSesame": false,
          "hasSoy": false,
          "hasBeef": true,
          "halalCertifiedMeat": true,
          "isSpicy": false,
          "isCarb": true,
          "hasCoconut": true
        }
      }
    }
  }
}