{
  "_meta": {
    "source": "KitchenDOOR",
    "site": "rexdale",
    "exported": "2026-05-13T23:35:51.979Z",
    "version": 30
  },
  "routing": {
    "1": {
      "SUNDAY": {
        "breakfast": {
          "Vegan / Vegetarian": 16,
          "Halal": 59,
          "Gluten Free": 3,
          "Diabetic": 6,
          "Regular": 88
        },
        "lunch": {
          "Vegan / Vegetarian": 16,
          "Gluten Free": 3,
          "Soft Meals": 5,
          "Regular": 148
        },
        "dinner": {
          "Vegan / Vegetarian": 15,
          "Gluten Free": 3,
          "Soft Meals": 5,
          "Regular": 149
        }
      },
      "MONDAY": {
        "breakfast": {
          "Vegan / Vegetarian": 16,
          "No Processed Food": 1,
          "Gluten Free": 3,
          "Soft Meals": 5,
          "No Egg / Mustard": 1,
          "Regular": 146
        },
        "lunch": {
          "Vegan / Vegetarian": 12,
          "No Processed Food": 1,
          "Gluten Free": 3,
          "Diabetic": 11,
          "Soft Meals": 5,
          "Regular": 140
        },
        "dinner": {
          "Vegan / Vegetarian": 12,
          "Diabetic": 12,
          "Bland": 3,
          "Soft Meals": 5,
          "Regular": 140
        }
      },
      "TUESDAY": {
        "breakfast": {
          "Vegan / Vegetarian": 16,
          "Gluten Free": 3,
          "Soft Meals": 5,
          "Regular": 148
        },
        "lunch": {
          "Vegan / Vegetarian": 14,
          "Soft Meals": 5,
          "Regular": 152,
          "Anaphylactic Alternative": 1
        },
        "dinner": {
          "Vegan / Vegetarian": 12,
          "Halal": 58,
          "Regular": 102
        }
      },
      "WEDNESDAY": {
        "breakfast": {
          "Vegan / Vegetarian": 16,
          "Gluten Free": 3,
          "Soft Meals": 5,
          "Regular": 148
        },
        "lunch": {
          "Vegan / Vegetarian": 16,
          "Halal": 59,
          "Gluten Free": 3,
          "Diabetic": 6,
          "Regular": 88
        },
        "dinner": {
          "Vegan / Vegetarian": 12,
          "Gluten Free": 3,
          "Diabetic": 12,
          "Soft Meals": 5,
          "Regular": 140
        }
      },
      "THURSDAY": {
        "breakfast": {
          "Vegan / Vegetarian": 16,
          "Halal": 59,
          "Gluten Free": 3,
          "Regular": 94
        },
        "lunch": {
          "Vegan / Vegetarian": 16,
          "Gluten Free": 3,
          "Diabetic": 12,
          "Bland": 3,
          "Soft Meals": 5,
          "No Egg / Mustard": 1,
          "Regular": 132
        },
        "dinner": {
          "Vegan / Vegetarian": 12,
          "Diabetic": 12,
          "Soft Meals": 5,
          "Regular": 143
        }
      },
      "FRIDAY": {
        "breakfast": {
          "Vegan / Vegetarian": 16,
          "Gluten Free": 3,
          "Soft Meals": 5,
          "No Egg / Mustard": 1,
          "Regular": 147
        },
        "lunch": {
          "Vegan / Vegetarian": 12,
          "Gluten Free": 3,
          "Soft Meals": 5,
          "No Egg / Mustard": 2,
          "Regular": 150
        },
        "dinner": {
          "Vegan / Vegetarian": 12,
          "Halal": 58,
          "Regular": 102
        }
      },
      "SATURDAY": {
        "breakfast": {
          "Vegan / Vegetarian": 16,
          "Gluten Free": 3,
          "Soft Meals": 5,
          "Regular": 148
        },
        "lunch": {
          "Vegan / Vegetarian": 12,
          "Gluten Free": 3,
          "Diabetic": 12,
          "Soft Meals": 5,
          "Regular": 140
        },
        "dinner": {
          "Vegan / Vegetarian": 15,
          "Soft Meals": 5,
          "Regular": 152
        }
      }
    },
    "2": {
      "SUNDAY": {
        "breakfast": {
          "Vegan / Vegetarian": 16,
          "Gluten Free": 3,
          "Diabetic": 12,
          "Soft Meals": 5,
          "No Egg / Mustard": 1,
          "Regular": 135
        },
        "lunch": {
          "Vegan / Vegetarian": 16,
          "Gluten Free": 3,
          "Soft Meals": 5,
          "Regular": 148
        },
        "dinner": {
          "Vegan / Vegetarian": 12,
          "Halal": 59,
          "Gluten Free": 3,
          "Diabetic": 6,
          "Regular": 92
        }
      },
      "MONDAY": {
        "breakfast": {
          "Vegan / Vegetarian": 16,
          "No Processed Food": 1,
          "Gluten Free": 3,
          "Soft Meals": 5,
          "No Egg / Mustard": 1,
          "Regular": 146
        },
        "lunch": {
          "Vegan / Vegetarian": 16,
          "Gluten Free": 3,
          "Bland": 3,
          "Soft Meals": 5,
          "Regular": 145
        },
        "dinner": {
          "Vegan / Vegetarian": 12,
          "Gluten Free": 3,
          "Diabetic": 11,
          "Bland": 3,
          "Soft Meals": 5,
          "Regular": 136,
          "Anaphylactic Alternative": 2
        }
      },
      "TUESDAY": {
        "breakfast": {
          "Vegan / Vegetarian": 16,
          "Gluten Free": 3,
          "Soft Meals": 5,
          "Regular": 148
        },
        "lunch": {
          "Vegan / Vegetarian": 12,
          "Halal": 58,
          "Gluten Free": 3,
          "Regular": 99
        },
        "dinner": {
          "Vegan / Vegetarian": 12,
          "Halal": 58,
          "Regular": 101
        }
      },
      "WEDNESDAY": {
        "breakfast": {
          "Vegan / Vegetarian": 16,
          "Gluten Free": 3,
          "Soft Meals": 5,
          "Regular": 148
        },
        "lunch": {
          "Vegan / Vegetarian": 12,
          "Gluten Free": 3,
          "Soft Meals": 5,
          "No Egg / Mustard": 2,
          "Regular": 150
        },
        "dinner": {
          "Vegan / Vegetarian": 14,
          "Diabetic": 12,
          "Soft Meals": 5,
          "Regular": 140,
          "Anaphylactic Alternative": 1
        }
      },
      "THURSDAY": {
        "breakfast": {
          "Vegan / Vegetarian": 16,
          "Halal": 59,
          "Gluten Free": 3,
          "Regular": 94
        },
        "lunch": {
          "Vegan / Vegetarian": 19,
          "Gluten Free": 3,
          "Soft Meals": 5,
          "Regular": 145
        },
        "dinner": {
          "Vegan / Vegetarian": 12,
          "Halal": 59,
          "Regular": 101
        }
      },
      "FRIDAY": {
        "breakfast": {
          "Vegan / Vegetarian": 16,
          "Halal": 59,
          "Gluten Free": 3,
          "Regular": 94
        },
        "lunch": {
          "Vegan / Vegetarian": 14,
          "Gluten Free": 2,
          "Diabetic": 12,
          "Soft Meals": 5,
          "Regular": 138,
          "Anaphylactic Alternative": 1
        },
        "dinner": {
          "Vegan / Vegetarian": 12,
          "Soft Meals": 5,
          "Regular": 155
        }
      },
      "SATURDAY": {
        "breakfast": {
          "Vegan / Vegetarian": 16,
          "Gluten Free": 3,
          "Soft Meals": 5,
          "Regular": 148
        },
        "lunch": {
          "Vegan / Vegetarian": 16,
          "Gluten Free": 3,
          "Soft Meals": 5,
          "Regular": 148
        },
        "dinner": {
          "Vegan / Vegetarian": 15,
          "Soft Meals": 5,
          "Regular": 152
        }
      }
    },
    "3": {
      "SUNDAY": {
        "breakfast": {
          "Vegan / Vegetarian": 16,
          "Halal": 59,
          "Gluten Free": 3,
          "Diabetic": 6,
          "Regular": 88
        },
        "lunch": {
          "Vegan / Vegetarian": 12,
          "Gluten Free": 3,
          "Diabetic": 12,
          "Soft Meals": 5,
          "No Egg / Mustard": 2,
          "Regular": 138
        },
        "dinner": {
          "Vegan / Vegetarian": 15,
          "Gluten Free": 3,
          "Diabetic": 11,
          "Soft Meals": 5,
          "Regular": 138
        }
      },
      "MONDAY": {
        "breakfast": {
          "Vegan / Vegetarian": 16,
          "No Processed Food": 1,
          "Gluten Free": 3,
          "Soft Meals": 5,
          "No Egg / Mustard": 1,
          "Regular": 146
        },
        "lunch": {
          "Vegan / Vegetarian": 12,
          "No Processed Food": 1,
          "Soft Meals": 5,
          "Regular": 154
        },
        "dinner": {
          "Vegan / Vegetarian": 12,
          "Diabetic": 12,
          "Soft Meals": 5,
          "Regular": 143
        }
      },
      "TUESDAY": {
        "breakfast": {
          "Vegan / Vegetarian": 16,
          "Gluten Free": 3,
          "Soft Meals": 5,
          "Regular": 148
        },
        "lunch": {
          "Vegan / Vegetarian": 12,
          "Halal": 59,
          "Diabetic": 6,
          "Regular": 95
        },
        "dinner": {
          "Vegan / Vegetarian": 12,
          "Gluten Free": 3,
          "Diabetic": 12,
          "Bland": 3,
          "Soft Meals": 5,
          "Regular": 137
        }
      },
      "WEDNESDAY": {
        "breakfast": {
          "Vegan / Vegetarian": 16,
          "Halal": 59,
          "Gluten Free": 3,
          "Regular": 94
        },
        "lunch": {
          "Vegan / Vegetarian": 16,
          "No Processed Food": 1,
          "Gluten Free": 3,
          "Diabetic": 11,
          "Soft Meals": 5,
          "Regular": 136
        },
        "dinner": {
          "Vegan / Vegetarian": 14,
          "Gluten Free": 2,
          "Soft Meals": 5,
          "Regular": 150,
          "Anaphylactic Alternative": 1
        }
      },
      "THURSDAY": {
        "breakfast": {
          "Vegan / Vegetarian": 16,
          "Halal": 59,
          "Gluten Free": 3,
          "Regular": 94
        },
        "lunch": {
          "Vegan / Vegetarian": 19,
          "Gluten Free": 3,
          "Diabetic": 11,
          "Soft Meals": 5,
          "Regular": 134
        },
        "dinner": {
          "Vegan / Vegetarian": 12,
          "Halal": 58,
          "Regular": 102
        }
      },
      "FRIDAY": {
        "breakfast": {
          "Vegan / Vegetarian": 16,
          "Halal": 59,
          "Gluten Free": 3,
          "Regular": 94
        },
        "lunch": {
          "Vegan / Vegetarian": 14,
          "Diabetic": 12,
          "Bland": 3,
          "Soft Meals": 5,
          "Regular": 137,
          "Anaphylactic Alternative": 1
        },
        "dinner": {
          "Vegan / Vegetarian": 12,
          "Diabetic": 12,
          "Soft Meals": 5,
          "Regular": 143
        }
      },
      "SATURDAY": {
        "breakfast": {
          "Vegan / Vegetarian": 16,
          "Gluten Free": 3,
          "Soft Meals": 5,
          "Regular": 148
        },
        "lunch": {
          "Vegan / Vegetarian": 12,
          "Soft Meals": 5,
          "Regular": 155
        },
        "dinner": {
          "Vegan / Vegetarian": 16,
          "Halal": 58,
          "Gluten Free": 3,
          "Diabetic": 7,
          "Regular": 88
        }
      }
    },
    "4": {
      "SUNDAY": {
        "breakfast": {
          "Vegan / Vegetarian": 16,
          "Gluten Free": 3,
          "Diabetic": 12,
          "Soft Meals": 5,
          "No Egg / Mustard": 1,
          "Regular": 135
        },
        "lunch": {
          "Vegan / Vegetarian": 16,
          "Halal": 58,
          "Gluten Free": 3,
          "Diabetic": 7,
          "Regular": 88
        },
        "dinner": {
          "Vegan / Vegetarian": 12,
          "Gluten Free": 3,
          "Diabetic": 12,
          "Bland": 3,
          "Soft Meals": 5,
          "Regular": 137
        }
      },
      "MONDAY": {
        "breakfast": {
          "Vegan / Vegetarian": 16,
          "No Processed Food": 1,
          "Gluten Free": 3,
          "Soft Meals": 5,
          "No Egg / Mustard": 1,
          "Regular": 146
        },
        "lunch": {
          "Vegan / Vegetarian": 16,
          "Gluten Free": 3,
          "Diabetic": 12,
          "Soft Meals": 5,
          "Regular": 136
        },
        "dinner": {
          "Vegan / Vegetarian": 14,
          "Diabetic": 12,
          "Bland": 3,
          "Soft Meals": 5,
          "Regular": 137,
          "Anaphylactic Alternative": 1
        }
      },
      "TUESDAY": {
        "breakfast": {
          "Vegan / Vegetarian": 16,
          "Gluten Free": 3,
          "Soft Meals": 5,
          "Regular": 148
        },
        "lunch": {
          "Vegan / Vegetarian": 12,
          "Halal": 58,
          "Gluten Free": 3,
          "Regular": 99
        },
        "dinner": {
          "Vegan / Vegetarian": 12,
          "Soft Meals": 5,
          "Regular": 155
        }
      },
      "WEDNESDAY": {
        "breakfast": {
          "Vegan / Vegetarian": 16,
          "Gluten Free": 3,
          "Soft Meals": 5,
          "Regular": 148
        },
        "lunch": {
          "Vegan / Vegetarian": 12,
          "Gluten Free": 3,
          "Soft Meals": 5,
          "No Egg / Mustard": 2,
          "Regular": 150
        },
        "dinner": {
          "Vegan / Vegetarian": 15,
          "Soft Meals": 5,
          "Regular": 152
        }
      },
      "THURSDAY": {
        "breakfast": {
          "Vegan / Vegetarian": 16,
          "Halal": 59,
          "Gluten Free": 3,
          "Regular": 94
        },
        "lunch": {
          "Vegan / Vegetarian": 12,
          "Halal": 53,
          "Gluten Free": 3,
          "Diabetic": 7,
          "Soft Meals": 5,
          "Regular": 92
        },
        "dinner": {
          "Vegan / Vegetarian": 12,
          "Gluten Free": 3,
          "Soft Meals": 5,
          "No Egg / Mustard": 2,
          "Regular": 150
        }
      },
      "FRIDAY": {
        "breakfast": {
          "Vegan / Vegetarian": 16,
          "Halal": 59,
          "Gluten Free": 3,
          "Regular": 94
        },
        "lunch": {
          "Vegan / Vegetarian": 19,
          "Gluten Free": 3,
          "Diabetic": 11,
          "Soft Meals": 5,
          "Regular": 134
        },
        "dinner": {
          "Vegan / Vegetarian": 12,
          "Halal": 58,
          "Diabetic": 7,
          "Regular": 94
        }
      },
      "SATURDAY": {
        "breakfast": {
          "Vegan / Vegetarian": 16,
          "Gluten Free": 3,
          "Soft Meals": 5,
          "Regular": 148
        },
        "lunch": {
          "Vegan / Vegetarian": 16,
          "Gluten Free": 3,
          "Diabetic": 12,
          "Soft Meals": 5,
          "Regular": 136
        },
        "dinner": {
          "Vegan / Vegetarian": 15,
          "Diabetic": 10,
          "Soft Meals": 5,
          "Regular": 140,
          "Anaphylactic Alternative": 2
        }
      }
    }
  }
}